base_converter/__init__.py
base_converter/__main__.py
base_converter/cli.py
base_converter/converter.py
base_converter/utils.py
floating_base_converter-1.0.0.dist-info/licenses/LICENSE
floating_base_converter-1.0.0.dist-info/METADATA
floating_base_converter-1.0.0.dist-info/WHEEL
floating_base_converter-1.0.0.dist-info/entry_points.txt
floating_base_converter-1.0.0.dist-info/top_level.txt
floating_base_converter-1.0.0.dist-info/RECORD
