Metadata-Version: 2.4
Name: floating-base-converter
Version: 1.0.0
Summary: A high-precision Python package for converting floating-point numbers between different bases with scientific notation support
Author-email: Yeabwang <wangxiayu@yeab.io>
Maintainer-email: Yeabwang <wangxiayu@yeab.io>
License: MIT
Project-URL: Homepage, https://github.com/yeabwang/floating-base-converter
Project-URL: Repository, https://github.com/yeabwang/floating-base-converter
Project-URL: Documentation, https://github.com/yeabwang/floating-base-converter#readme
Project-URL: Changelog, https://github.com/yeabwang/floating-base-converter/blob/main/CHANGELOG.md
Project-URL: Bug Tracker, https://github.com/yeabwang/floating-base-converter/issues
Keywords: base conversion,floating point,binary,octal,hexadecimal,decimal,number systems
Classifier: Development Status :: 3 - Alpha
Classifier: Intended Audience :: Developers
Classifier: Operating System :: OS Independent
Classifier: Programming Language :: Python :: 3
Classifier: Programming Language :: Python :: 3.8
Classifier: Programming Language :: Python :: 3.9
Classifier: Programming Language :: Python :: 3.10
Classifier: Programming Language :: Python :: 3.11
Classifier: Programming Language :: Python :: 3.12
Classifier: Topic :: Scientific/Engineering :: Mathematics
Classifier: Topic :: Software Development :: Libraries :: Python Modules
Classifier: Topic :: Utilities
Requires-Python: >=3.8
License-File: LICENSE
Provides-Extra: dev
Requires-Dist: pytest>=7.0; extra == "dev"
Requires-Dist: pytest-cov>=4.0; extra == "dev"
Requires-Dist: black>=23.0; extra == "dev"
Requires-Dist: flake8>=6.0; extra == "dev"
Requires-Dist: mypy>=1.0; extra == "dev"
Requires-Dist: twine>=4.0; extra == "dev"
Requires-Dist: build>=0.10; extra == "dev"
Dynamic: license-file
